jupytercad_urdf/__init__.py
jupytercad_urdf/_version.py
jupytercad_urdf-0.1.4.data/data/share/jupyter/labextensions/@jupytercad/jupytercad-urdf/build_log.json
jupytercad_urdf-0.1.4.data/data/share/jupyter/labextensions/@jupytercad/jupytercad-urdf/package.json
jupytercad_urdf-0.1.4.data/data/share/jupyter/labextensions/@jupytercad/jupytercad-urdf/schemas/@jupytercad/jupytercad-urdf/package.json.orig
jupytercad_urdf-0.1.4.data/data/share/jupyter/labextensions/@jupytercad/jupytercad-urdf/schemas/@jupytercad/jupytercad-urdf/plugin.json
jupytercad_urdf-0.1.4.data/data/share/jupyter/labextensions/@jupytercad/jupytercad-urdf/static/lib_index_js.8c139949b2e4ce196256.js
jupytercad_urdf-0.1.4.data/data/share/jupyter/labextensions/@jupytercad/jupytercad-urdf/static/lib_index_js.8c139949b2e4ce196256.js.map
jupytercad_urdf-0.1.4.data/data/share/jupyter/labextensions/@jupytercad/jupytercad-urdf/static/remoteEntry.3a0dce97afdd1f71d1c8.js
jupytercad_urdf-0.1.4.data/data/share/jupyter/labextensions/@jupytercad/jupytercad-urdf/static/remoteEntry.3a0dce97afdd1f71d1c8.js.map
jupytercad_urdf-0.1.4.data/data/share/jupyter/labextensions/@jupytercad/jupytercad-urdf/static/style.js
jupytercad_urdf-0.1.4.data/data/share/jupyter/labextensions/@jupytercad/jupytercad-urdf/static/style_index_js.699184cfd1b5949609c8.js
jupytercad_urdf-0.1.4.data/data/share/jupyter/labextensions/@jupytercad/jupytercad-urdf/static/style_index_js.699184cfd1b5949609c8.js.map
jupytercad_urdf-0.1.4.data/data/share/jupyter/labextensions/@jupytercad/jupytercad-urdf/static/vendors-node_modules_ajv_dist_ajv_js.4684a8c0d698404c437c.js
jupytercad_urdf-0.1.4.data/data/share/jupyter/labextensions/@jupytercad/jupytercad-urdf/static/vendors-node_modules_ajv_dist_ajv_js.4684a8c0d698404c437c.js.map
jupytercad_urdf-0.1.4.data/data/share/jupyter/labextensions/@jupytercad/jupytercad-urdf/static/vendors-node_modules_d3-color_src_index_js.40bb9aa82fa850d4399b.js
jupytercad_urdf-0.1.4.dist-info/METADATA
jupytercad_urdf-0.1.4.dist-info/WHEEL
jupytercad_urdf-0.1.4.dist-info/licenses/LICENSE
jupytercad_urdf-0.1.4.dist-info/RECORD
