Metadata-Version: 2.4
Name: jupytercad_urdf
Version: 0.1.4
Summary: A JupyterCAD URDF export extension.
Project-URL: Homepage, https://github.com/jupytercad/JupyterCAD-urdf
Project-URL: Bug Tracker, https://github.com/jupytercad/JupyterCAD-urdf/issues
Project-URL: Repository, https://github.com/jupytercad/JupyterCAD-urdf.git
Author-email: Yahia HENI <yahia.heni@quantstack.net>
License: BSD 3-Clause License
License-File: LICENSE
Keywords: jupyter,jupyterlab,jupyterlab-extension
Classifier: Framework :: Jupyter
Classifier: Framework :: Jupyter :: JupyterLab
Classifier: Framework :: Jupyter :: JupyterLab :: 4
Classifier: Framework :: Jupyter :: JupyterLab :: Extensions
Classifier: Framework :: Jupyter :: JupyterLab :: Extensions :: Prebuilt
Classifier: License :: OSI Approved :: BSD License
Classifier: Programming Language :: Python
Classifier: Programming Language :: Python :: 3
Classifier: Programming Language :: Python :: 3.9
Classifier: Programming Language :: Python :: 3.10
Classifier: Programming Language :: Python :: 3.11
Classifier: Programming Language :: Python :: 3.12
Classifier: Programming Language :: Python :: 3.13
Requires-Python: >=3.9
